[
  {
    "assetId": "AST-001",
    "name": "Heysham 1",
    "nodeId": "NODE-HEY",
    "nodeName": "Heysham",
    "region": "North West",
    "country": "Great Britain",
    "technology": "AGR nuclear",
    "netMw": 1155,
    "retirementDate": "2028-03-31",
    "retirementClass": "Likely",
    "confidenceScore": 100,
    "evidenceSource": "Analyst proxy (MW-scaled) — overwrite with evidenced values",
    "notes": "",
    "status": "Active",
    "inertiaProxy": 5775,
    "faultLevelProxy": 1270.5,
    "reactiveProxy": 381.2,
    "latitude": 54.0289,
    "longitude": -2.9161,
    "hasCoordinates": true,
    "retirementBasis": "Confirmed",
    "modelledRetirementYear": 2028,
    "modelledRetirementReason": "Existing register assumption"
  },
  {
    "assetId": "AST-002",
    "name": "Hartlepool",
    "nodeId": "NODE-HPL",
    "nodeName": "Hartlepool",
    "region": "North East",
    "country": "Great Britain",
    "technology": "AGR nuclear",
    "netMw": 1185,
    "retirementDate": "2028-03-31",
    "retirementClass": "Likely",
    "confidenceScore": 100,
    "evidenceSource": "Analyst proxy (MW-scaled) — overwrite with evidenced values",
    "notes": "",
    "status": "Active",
    "inertiaProxy": 5925,
    "faultLevelProxy": 1303.5,
    "reactiveProxy": 391.1,
    "latitude": 54.635,
    "longitude": -1.182,
    "hasCoordinates": true,
    "retirementBasis": "Confirmed",
    "modelledRetirementYear": 2028,
    "modelledRetirementReason": "Existing register assumption"
  },
  {
    "assetId": "AST-003",
    "name": "Heysham 2",
    "nodeId": "NODE-HEY",
    "nodeName": "Heysham",
    "region": "North West",
    "country": "Great Britain",
    "technology": "AGR nuclear",
    "netMw": 1230,
    "retirementDate": "2030-03-31",
    "retirementClass": "Likely",
    "confidenceScore": 100,
    "evidenceSource": "Analyst proxy (MW-scaled) — overwrite with evidenced values",
    "notes": "",
    "status": "Active",
    "inertiaProxy": 6150,
    "faultLevelProxy": 1353,
    "reactiveProxy": 405.9,
    "latitude": 54.0289,
    "longitude": -2.9161,
    "hasCoordinates": true,
    "retirementBasis": "Confirmed",
    "modelledRetirementYear": 2030,
    "modelledRetirementReason": "Existing register assumption"
  },
  {
    "assetId": "AST-004",
    "name": "Torness",
    "nodeId": "NODE-TOR",
    "nodeName": "Torness",
    "region": "Scotland",
    "country": "Great Britain",
    "technology": "AGR nuclear",
    "netMw": 1190,
    "retirementDate": "2030-03-31",
    "retirementClass": "Likely",
    "confidenceScore": 100,
    "evidenceSource": "Analyst proxy (MW-scaled) — overwrite with evidenced values",
    "notes": "",
    "status": "Active",
    "inertiaProxy": 5950,
    "faultLevelProxy": 1309,
    "reactiveProxy": 392.7,
    "latitude": 55.968,
    "longitude": -2.4091,
    "hasCoordinates": true,
    "retirementBasis": "Confirmed",
    "modelledRetirementYear": 2030,
    "modelledRetirementReason": "Existing register assumption"
  },
  {
    "assetId": "AST-005",
    "name": "Sizewell B",
    "nodeId": "NODE-SIZ",
    "nodeName": "Sizewell",
    "region": "East of England",
    "country": "Great Britain",
    "technology": "PWR nuclear",
    "netMw": 1198,
    "retirementDate": "2055-03-31",
    "retirementClass": "Likely",
    "confidenceScore": 100,
    "evidenceSource": "CfD signed 8 Jul 2026 — 20-yr life extension to Mar 2055 (gov.uk, Reuters, WNN)",
    "notes": "",
    "status": "Active",
    "inertiaProxy": 5990,
    "faultLevelProxy": 1317.8,
    "reactiveProxy": 395.3,
    "latitude": 52.213,
    "longitude": 1.621,
    "hasCoordinates": true,
    "retirementBasis": "Confirmed",
    "modelledRetirementYear": 2055,
    "modelledRetirementReason": "Existing register assumption"
  },
  {
    "assetId": "AST-006",
    "name": "Drax Power Station",
    "nodeId": "NODE-DRX",
    "nodeName": "Drax",
    "region": "Yorkshire",
    "country": "Great Britain",
    "technology": "Biomass steam turbine",
    "netMw": 2595,
    "retirementDate": "2031-03-31",
    "retirementClass": "Possible",
    "confidenceScore": 60,
    "evidenceSource": "LCD CfD signed 5 Nov 2025 — 4 biomass units contracted Apr 2027–Mar 2031 (Drax RNS)",
    "notes": "",
    "status": "Active",
    "inertiaProxy": 12975,
    "faultLevelProxy": 2854.5,
    "reactiveProxy": 856.4,
    "latitude": 53.744,
    "longitude": -0.993,
    "hasCoordinates": true,
    "retirementBasis": "Modelled",
    "modelledRetirementYear": 2036,
    "modelledRetirementReason": "Drax has a low-carbon dispatchable CfD covering April 2027 to March 2031"
  },
  {
    "assetId": "AST-007",
    "name": "Severn Power",
    "nodeId": "NODE-SEV",
    "nodeName": "Uskmouth / Severn",
    "region": "South Wales",
    "country": "Great Britain",
    "technology": "CCGT",
    "netMw": 850,
    "retirementClass": "Unclear",
    "confidenceScore": 65,
    "evidenceSource": "Analyst proxy (MW-scaled) — overwrite with evidenced values",
    "notes": "",
    "status": "Active",
    "inertiaProxy": 4250,
    "faultLevelProxy": 935,
    "reactiveProxy": 280.5,
    "latitude": 51.568,
    "longitude": -2.938,
    "hasCoordinates": true,
    "retirementBasis": "Modelled",
    "modelledRetirementYear": 2045,
    "modelledRetirementReason": "34-year operating life - commisioned 2001"
  },
  {
    "assetId": "AST-008",
    "name": "Didcot B",
    "nodeId": "NODE-DID",
    "nodeName": "Didcot",
    "region": "South East",
    "country": "Great Britain",
    "technology": "CCGT",
    "netMw": 1440,
    "retirementClass": "Unclear",
    "confidenceScore": 55,
    "evidenceSource": "Analyst proxy (MW-scaled) — overwrite with evidenced values",
    "notes": "",
    "status": "Active",
    "inertiaProxy": 7200,
    "faultLevelProxy": 1584,
    "reactiveProxy": 475.2,
    "latitude": 51.624,
    "longitude": -1.268,
    "hasCoordinates": true,
    "retirementBasis": "Modelled",
    "modelledRetirementYear": 2032,
    "modelledRetirementReason": "Commissioned 1997 ~35 years of operation."
  },
  {
    "assetId": "AST-009",
    "name": "Staythorpe",
    "nodeId": "NODE-STY",
    "nodeName": "Staythorpe",
    "region": "East Midlands",
    "country": "Great Britain",
    "technology": "CCGT",
    "netMw": 1850,
    "retirementClass": "Unclear",
    "confidenceScore": 65,
    "evidenceSource": "Analyst proxy (MW-scaled) — overwrite with evidenced values",
    "notes": "",
    "status": "Active",
    "inertiaProxy": 9250,
    "faultLevelProxy": 2035,
    "reactiveProxy": 610.5,
    "latitude": 53.163,
    "longitude": -0.777,
    "hasCoordinates": true,
    "retirementBasis": "Modelled",
    "modelledRetirementYear": 2045,
    "modelledRetirementReason": "Design-life proxy (~35 years)"
  },
  {
    "assetId": "AST-010",
    "name": "Pembroke",
    "nodeId": "NODE-PEM",
    "nodeName": "Pembroke",
    "region": "South Wales",
    "country": "Great Britain",
    "technology": "CCGT",
    "netMw": 2181,
    "retirementClass": "Unclear",
    "confidenceScore": 65,
    "evidenceSource": "Analyst proxy (MW-scaled) — overwrite with evidenced values",
    "notes": "",
    "status": "Active",
    "inertiaProxy": 10905,
    "faultLevelProxy": 2399.1,
    "reactiveProxy": 719.7,
    "latitude": 51.696,
    "longitude": -4.94,
    "hasCoordinates": true,
    "retirementBasis": "Modelled",
    "modelledRetirementYear": 2047,
    "modelledRetirementReason": "Design-life proxy (35 year operating life)"
  },
  {
    "assetId": "AST-011",
    "name": "Keadby 1",
    "nodeId": "NODE-KEA",
    "nodeName": "Keadby / Brigg",
    "region": "Yorkshire & Humber",
    "country": "Great Britain",
    "technology": "CCGT",
    "netMw": 732,
    "retirementClass": "Unclear",
    "confidenceScore": 50,
    "evidenceSource": "Analyst proxy (MW-scaled) — overwrite with evidenced values",
    "notes": "",
    "status": "Active",
    "inertiaProxy": 3675,
    "faultLevelProxy": 808.5,
    "reactiveProxy": 242.6,
    "latitude": 53.588,
    "longitude": -0.689,
    "hasCoordinates": true,
    "retirementBasis": "Modelled",
    "modelledRetirementYear": 2031,
    "modelledRetirementReason": "strategic generation hub with continuing site investment"
  },
  {
    "assetId": "AST-012",
    "name": "Brigg legacy CCGT",
    "nodeId": "NODE-KEA",
    "nodeName": "Keadby / Brigg",
    "region": "Yorkshire & Humber",
    "country": "Great Britain",
    "technology": "Legacy CCGT",
    "netMw": 240,
    "retirementDate": "2020-12-31",
    "retirementClass": "Likely",
    "confidenceScore": 100,
    "evidenceSource": "Analyst proxy (MW-scaled) — overwrite with evidenced values",
    "notes": "",
    "status": "Active",
    "inertiaProxy": 1200,
    "faultLevelProxy": 264,
    "reactiveProxy": 79.2,
    "latitude": 53.588,
    "longitude": -0.689,
    "hasCoordinates": true,
    "retirementBasis": "Confirmed",
    "modelledRetirementYear": 2020,
    "modelledRetirementReason": "Existing register assumption"
  },
  {
    "assetId": "AST-013",
    "name": "Ratcliffe-on-Soar",
    "nodeId": "NODE-RAT",
    "nodeName": "Ratcliffe",
    "region": "East Midlands",
    "country": "Great Britain",
    "technology": "Legacy coal steam turbine",
    "netMw": 2115,
    "retirementDate": "2024-09-30",
    "retirementClass": "Likely",
    "confidenceScore": 100,
    "evidenceSource": "Analyst proxy (MW-scaled) — overwrite with evidenced values",
    "notes": "",
    "status": "Active",
    "inertiaProxy": 10575,
    "faultLevelProxy": 2326.5,
    "reactiveProxy": 698,
    "latitude": 52.877,
    "longitude": -1.275,
    "hasCoordinates": true,
    "retirementBasis": "Confirmed",
    "modelledRetirementYear": 2024,
    "modelledRetirementReason": "Existing register assumption"
  },
  {
    "assetId": "AST-014",
    "name": "Lynemouth",
    "nodeId": "NODE-LYN",
    "nodeName": "Lynemouth",
    "region": "North East",
    "country": "Great Britain",
    "technology": "Biomass steam turbine (converted coal)",
    "netMw": 420,
    "retirementDate": "2031-03-31",
    "retirementClass": "Likely",
    "confidenceScore": 60,
    "evidenceSource": "LCD CfD signed 9 Jul 2026 — subsidy Apr 2027–Mar 2031 (DESNZ / gov.uk)",
    "notes": "",
    "status": "Active",
    "inertiaProxy": 2100,
    "faultLevelProxy": 462,
    "reactiveProxy": 138.6,
    "latitude": 55.129,
    "longitude": -1.508,
    "hasCoordinates": true,
    "retirementBasis": "Modelled",
    "modelledRetirementYear": 2036,
    "modelledRetirementReason": "aligns with biomass support ending; no evidence of plant retirement"
  },
  {
    "assetId": "AST-015",
    "name": "MGT Teesside (Tees REP)",
    "nodeId": "NODE-TEE",
    "nodeName": "Teesport",
    "region": "North East",
    "country": "Great Britain",
    "technology": "Biomass CHP",
    "netMw": 299,
    "retirementClass": "Possible",
    "confidenceScore": 55,
    "evidenceSource": "RO-backed to ~2042; retirement date unclear",
    "notes": "",
    "status": "Active",
    "inertiaProxy": 1495,
    "faultLevelProxy": 328.9,
    "reactiveProxy": 98.7,
    "latitude": 54.635,
    "longitude": -1.15,
    "hasCoordinates": true,
    "retirementBasis": "Modelled",
    "modelledRetirementYear": 2045,
    "modelledRetirementReason": "RO-backed to ~2042; retirement date unclear"
  },
  {
    "assetId": "AST-016",
    "name": "Dinorwig",
    "nodeId": "NODE-PEN",
    "nodeName": "Pentir",
    "region": "North Wales",
    "country": "Great Britain",
    "technology": "Pumped storage hydro",
    "netMw": 1728,
    "retirementDate": "2050-12-31",
    "retirementClass": "Unlikely / Not possible",
    "confidenceScore": 85,
    "evidenceSource": "£1bn ENGIE/CDPQ replant — ≥25 yr life extension, first units re-commissioning 2028/29",
    "notes": "",
    "status": "Active",
    "inertiaProxy": 8640,
    "faultLevelProxy": 1900.8,
    "reactiveProxy": 570.2,
    "latitude": 53.184,
    "longitude": -4.172,
    "hasCoordinates": true,
    "retirementBasis": "Modelled",
    "modelledRetirementYear": 2055,
    "modelledRetirementReason": "Long-life hydro with active replanting programme."
  },
  {
    "assetId": "AST-017",
    "name": "Ffestiniog",
    "nodeId": "NODE-TRA",
    "nodeName": "Trawsfynydd",
    "region": "North Wales",
    "country": "Great Britain",
    "technology": "Pumped storage hydro",
    "netMw": 360,
    "retirementDate": "2051-07-31",
    "retirementClass": "Unlikely / Not possible",
    "confidenceScore": 85,
    "evidenceSource": "9-yr replant completing Jul 2026 — ≥25 yr life extension",
    "notes": "",
    "status": "Active",
    "inertiaProxy": 1800,
    "faultLevelProxy": 396,
    "reactiveProxy": 118.8,
    "latitude": 52.928,
    "longitude": -3.936,
    "hasCoordinates": true,
    "retirementBasis": "Modelled",
    "modelledRetirementYear": 2051,
    "modelledRetirementReason": "Refurbished pumped storage, +25-year life assumption."
  },
  {
    "assetId": "AST-018",
    "name": "Cruachan 1",
    "nodeId": "NODE-CRU",
    "nodeName": "Dalmally",
    "region": "Scotland",
    "country": "Great Britain",
    "technology": "Pumped storage hydro",
    "netMw": 480,
    "retirementDate": "2050-12-31",
    "retirementClass": "Unlikely / Not possible",
    "confidenceScore": 80,
    "evidenceSource": "£80m Drax refurb (units 3 & 4); capacity uprated 440 → 480 MW",
    "notes": "",
    "status": "Active",
    "inertiaProxy": 2400,
    "faultLevelProxy": 528,
    "reactiveProxy": 158.4,
    "latitude": 56.391,
    "longitude": -5.112,
    "hasCoordinates": true,
    "retirementBasis": "Modelled",
    "modelledRetirementYear": 2050,
    "modelledRetirementReason": "Drax/ANDRITZ confirm £80m upgrade to raise capacity to 480 MW and extend lifecycle."
  },
  {
    "assetId": "AST-019",
    "name": "Foyers",
    "nodeId": "NODE-FOY",
    "nodeName": "Fort Augustus",
    "region": "Scotland",
    "country": "Great Britain",
    "technology": "Pumped storage hydro",
    "netMw": 300,
    "retirementDate": "2045-12-31",
    "retirementClass": "Possible",
    "confidenceScore": 60,
    "evidenceSource": "50-yr milestone reached 2024; SSE retains asset (no confirmed retirement)",
    "notes": "",
    "status": "Active",
    "inertiaProxy": 1500,
    "faultLevelProxy": 330,
    "reactiveProxy": 99,
    "latitude": 57.136,
    "longitude": -4.675,
    "hasCoordinates": true,
    "retirementBasis": "Modelled",
    "modelledRetirementYear": 2045,
    "modelledRetirementReason": "Old pumped storage asset, operational but no clear replanting date found."
  },
  {
    "assetId": "AST-020",
    "name": "Little Barford",
    "nodeId": "NODE-LBF",
    "nodeName": "Little Barford",
    "region": "East of England",
    "country": "Great Britain",
    "technology": "CCGT",
    "netMw": 727,
    "retirementClass": "Unclear",
    "confidenceScore": 50,
    "evidenceSource": "Design-life proxy (comm. 1994 + 30 yrs); no CM exit signalled",
    "notes": "",
    "status": "Active",
    "inertiaProxy": 3635,
    "faultLevelProxy": 799.7,
    "reactiveProxy": 239.9,
    "latitude": 52.21,
    "longitude": -0.283,
    "hasCoordinates": true,
    "retirementBasis": "Modelled",
    "modelledRetirementYear": 2030,
    "modelledRetirementReason": "35-year proxy from 1995."
  },
  {
    "assetId": "AST-021",
    "name": "Medway",
    "nodeId": "NODE-GRA",
    "nodeName": "Isle of Grain",
    "region": "South East",
    "country": "Great Britain",
    "technology": "CCGT",
    "netMw": 735,
    "retirementClass": "Unclear",
    "confidenceScore": 50,
    "evidenceSource": "Design-life proxy (comm. 1995 + 30 yrs)",
    "notes": "",
    "status": "Active",
    "inertiaProxy": 3675,
    "faultLevelProxy": 808.5,
    "reactiveProxy": 242.6,
    "latitude": 51.447,
    "longitude": 0.724,
    "hasCoordinates": true,
    "retirementBasis": "Modelled",
    "modelledRetirementYear": 2030,
    "modelledRetirementReason": "35-year proxy from 1995."
  },
  {
    "assetId": "AST-022",
    "name": "Connah's Quay",
    "nodeId": "NODE-CNQ",
    "nodeName": "Connah's Quay",
    "region": "North Wales",
    "country": "Great Britain",
    "technology": "CCGT",
    "netMw": 1380,
    "retirementClass": "Possible",
    "confidenceScore": 65,
    "evidenceSource": "Uniper planning CCGT+CCS replacement online by 2030 (HyNet cluster)",
    "notes": "",
    "status": "Active",
    "inertiaProxy": 6900,
    "faultLevelProxy": 1518,
    "reactiveProxy": 455.4,
    "latitude": 53.217,
    "longitude": -3.056,
    "hasCoordinates": true,
    "retirementBasis": "Modelled",
    "modelledRetirementYear": 2030,
    "modelledRetirementReason": "Replacement strategy points to existing unabated plant risk around 2030."
  },
  {
    "assetId": "AST-023",
    "name": "Keadby 2",
    "nodeId": "NODE-KEA",
    "nodeName": "Keadby / Brigg",
    "region": "Yorkshire & Humber",
    "country": "Great Britain",
    "technology": "CCGT (H-class)",
    "netMw": 893,
    "retirementClass": "Unclear",
    "confidenceScore": 60,
    "evidenceSource": "Modern H-class; design-life proxy (comm. 2023 + 30 yrs)",
    "notes": "",
    "status": "Active",
    "inertiaProxy": 4465,
    "faultLevelProxy": 982.3,
    "reactiveProxy": 294.7,
    "latitude": 53.588,
    "longitude": -0.689,
    "hasCoordinates": true,
    "retirementBasis": "Modelled",
    "modelledRetirementYear": 2058,
    "modelledRetirementReason": "35-year proxy from 2023; very new efficient CCGT."
  },
  {
    "assetId": "AST-024",
    "name": "Sutton Bridge",
    "nodeId": "NODE-STB",
    "nodeName": "Sutton Bridge",
    "region": "East Midlands",
    "country": "Great Britain",
    "technology": "CCGT",
    "netMw": 819,
    "retirementClass": "Unclear",
    "confidenceScore": 45,
    "evidenceSource": "Design-life proxy (comm. 1999 + 30 yrs)",
    "notes": "",
    "status": "Active",
    "inertiaProxy": 4095,
    "faultLevelProxy": 900.9,
    "reactiveProxy": 270.3,
    "latitude": 52.769,
    "longitude": 0.185,
    "hasCoordinates": true,
    "retirementBasis": "Modelled",
    "modelledRetirementYear": 2034,
    "modelledRetirementReason": "35-year proxy, but mothballing history lowers confidence."
  },
  {
    "assetId": "AST-025",
    "name": "Saltend CHP",
    "nodeId": "NODE-SLT",
    "nodeName": "Saltend",
    "region": "Yorkshire & Humber",
    "country": "Great Britain",
    "technology": "CCGT CHP",
    "netMw": 1200,
    "retirementClass": "Unclear",
    "confidenceScore": 55,
    "evidenceSource": "Design-life proxy (comm. 2000 + 30 yrs); supplies Saltend Chemicals Park",
    "notes": "",
    "status": "Active",
    "inertiaProxy": 6000,
    "faultLevelProxy": 1320,
    "reactiveProxy": 396,
    "latitude": 53.734,
    "longitude": -0.204,
    "hasCoordinates": true,
    "retirementBasis": "Modelled",
    "modelledRetirementYear": 2040,
    "modelledRetirementReason": "CHP/industrial role and hydrogen pathway support life extension beyond simple 2035 proxy."
  },
  {
    "assetId": "AST-026",
    "name": "Damhead Creek",
    "nodeId": "NODE-DHC",
    "nodeName": "Damhead Creek",
    "region": "South East",
    "country": "Great Britain",
    "technology": "CCGT",
    "netMw": 805,
    "retirementClass": "Possible",
    "confidenceScore": 50,
    "evidenceSource": "VPI exploring 900 MW CCGT+CCS replacement online by 2030",
    "notes": "",
    "status": "Active",
    "inertiaProxy": 4025,
    "faultLevelProxy": 885.5,
    "reactiveProxy": 265.7,
    "latitude": 51.433,
    "longitude": 0.54,
    "hasCoordinates": true,
    "retirementBasis": "Modelled",
    "modelledRetirementYear": 2035,
    "modelledRetirementReason": "35-year proxy from 2000/2001."
  },
  {
    "assetId": "AST-027",
    "name": "Immingham CHP (VPI)",
    "nodeId": "NODE-IMM",
    "nodeName": "Immingham",
    "region": "Yorkshire & Humber",
    "country": "Great Britain",
    "technology": "CCGT CHP",
    "netMw": 1240,
    "retirementDate": "2040-12-31",
    "retirementClass": "Possible",
    "confidenceScore": 60,
    "evidenceSource": "Viking CCS retrofit planned — VPI: \"operate into 2030s and beyond\"",
    "notes": "",
    "status": "Active",
    "inertiaProxy": 6200,
    "faultLevelProxy": 1364,
    "reactiveProxy": 409.2,
    "latitude": 53.631,
    "longitude": -0.195,
    "hasCoordinates": true,
    "retirementBasis": "Modelled",
    "modelledRetirementYear": 2040,
    "modelledRetirementReason": "CCS plans support operation beyond 2030"
  },
  {
    "assetId": "AST-028",
    "name": "West Burton B",
    "nodeId": "NODE-WBB",
    "nodeName": "West Burton",
    "region": "East Midlands",
    "country": "Great Britain",
    "technology": "CCGT",
    "netMw": 1270,
    "retirementClass": "Unclear",
    "confidenceScore": 50,
    "evidenceSource": "Design-life proxy (comm. 2013 + 30 yrs); TotalEnergies owned",
    "notes": "",
    "status": "Active",
    "inertiaProxy": 6350,
    "faultLevelProxy": 1397,
    "reactiveProxy": 419.1,
    "latitude": 53.274,
    "longitude": -0.793,
    "hasCoordinates": true,
    "retirementBasis": "Modelled",
    "modelledRetirementYear": 2038,
    "modelledRetirementReason": "Mid-2000s CCGT with no announced replacement or closure programme."
  },
  {
    "assetId": "AST-029",
    "name": "Peterhead",
    "nodeId": "NODE-PHD",
    "nodeName": "Peterhead",
    "region": "Scotland",
    "country": "Great Britain",
    "technology": "CCGT",
    "netMw": 1180,
    "retirementDate": "2040-12-31",
    "retirementClass": "Likely",
    "confidenceScore": 55,
    "evidenceSource": "SSE states existing station runs concurrently with Peterhead 2 CCS until 2040",
    "notes": "",
    "status": "Active",
    "inertiaProxy": 5900,
    "faultLevelProxy": 1298,
    "reactiveProxy": 389.4,
    "latitude": 57.486,
    "longitude": -1.786,
    "hasCoordinates": true,
    "retirementBasis": "Modelled",
    "modelledRetirementYear": 2045,
    "modelledRetirementReason": "Planned CCS successor at the site suggests continued operation into the 2040s"
  },
  {
    "assetId": "AST-030",
    "name": "Keadby 3 (CCS)",
    "nodeId": "NODE-KEA",
    "nodeName": "Keadby / Brigg",
    "region": "Yorkshire & Humber",
    "country": "Great Britain",
    "technology": "CCGT + CCS (new build)",
    "netMw": 910,
    "retirementDate": "2055-12-31",
    "retirementClass": "Unlikely / Not possible",
    "confidenceScore": 70,
    "evidenceSource": "DCO granted Dec 2022; target commissioning late-2020s",
    "notes": "",
    "status": "Active",
    "inertiaProxy": 4550,
    "faultLevelProxy": 1001,
    "reactiveProxy": 300.3,
    "latitude": 53.588,
    "longitude": -0.689,
    "hasCoordinates": true,
    "retirementBasis": "Modelled",
    "modelledRetirementYear": 2055,
    "modelledRetirementReason": "New-build CCS plant with expected multi-decade operational life."
  },
  {
    "assetId": "AST-031",
    "name": "Peterhead 2 (CCS)",
    "nodeId": "NODE-PHD",
    "nodeName": "Peterhead",
    "region": "Scotland",
    "country": "Great Britain",
    "technology": "CCGT + CCS (new build)",
    "netMw": 900,
    "retirementDate": "2055-12-31",
    "retirementClass": "Unlikely / Not possible",
    "confidenceScore": 55,
    "evidenceSource": "SSE/Equinor project — targeted operation 2030–2055",
    "notes": "",
    "status": "Active",
    "inertiaProxy": 4500,
    "faultLevelProxy": 990,
    "reactiveProxy": 297,
    "latitude": 57.486,
    "longitude": -1.786,
    "hasCoordinates": true,
    "retirementBasis": "Modelled",
    "modelledRetirementYear": 2055,
    "modelledRetirementReason": "New-build CCS plant with no identified closure driver."
  },
  {
    "assetId": "AST-032",
    "name": "Staythorpe (CCS retrofit)",
    "nodeId": "NODE-STY",
    "nodeName": "Staythorpe",
    "region": "East Midlands",
    "country": "Great Britain",
    "technology": "CCGT + CCS (retrofit)",
    "netMw": 1500,
    "retirementDate": "2050-12-31",
    "retirementClass": "Unlikely / Not possible",
    "confidenceScore": 65,
    "evidenceSource": "RWE DCO submitted for 1.5 GW post-combustion CCS retrofit — extends life to 2050+",
    "notes": "",
    "status": "Active",
    "inertiaProxy": 7500,
    "faultLevelProxy": 1650,
    "reactiveProxy": 495,
    "latitude": 53.163,
    "longitude": -0.777,
    "hasCoordinates": true,
    "retirementBasis": "Modelled",
    "modelledRetirementYear": 2050,
    "modelledRetirementReason": "CCS retrofit is specifically intended to keep Staythorpe operating as a decarbonised plant well beyond its original gas-only life."
  }
]